openbankingbr/__init__.py
openbankingbr/__version__.py
openbankingbr/batch.py
openbankingbr/errors.py
openbankingbr/models.py
openbankingbr/spec.py
openbankingbr/utils.py
openbankingbr-0.1.4.dist-info/LICENSE
openbankingbr-0.1.4.dist-info/METADATA
openbankingbr-0.1.4.dist-info/WHEEL
openbankingbr-0.1.4.dist-info/top_level.txt
openbankingbr-0.1.4.dist-info/RECORD
