Metadata-Version: 2.1
Name: openbankingbr
Version: 0.1.4
Summary: Python 3 package to extract public data for Open Banking Brasil.
Home-page: https://github.com/knuppe/openbankingbr
Author: Gustavo J Knuppe
Author-email: gustavoknuppe@gmail.com
License: MIT
Project-URL: Bug Tracker, https://github.com/knuppe/openbankingbr/issues
Keywords: openbanking,bacen,banco-central-brasil
Platform: UNKNOWN
Classifier: Development Status :: 3 - Alpha
Classifier: Intended Audience :: Developers
Classifier: License :: OSI Approved :: MIT License
Classifier: Natural Language :: Portuguese (Brazilian)
Classifier: Programming Language :: Python :: 3
Classifier: Operating System :: OS Independent
Requires-Python: >=3.6
Requires-Dist: requests
